tts_webui_extension/megatts3/__init__.py
tts_webui_extension/megatts3/main.py
tts_webui_extension/megatts3/tts.py
tts_webui_extension/megatts3/ui.py
tts_webui_extension_megatts3-0.0.1.dist-info/licenses/LICENSE
tts_webui_extension_megatts3-0.0.1.dist-info/METADATA
tts_webui_extension_megatts3-0.0.1.dist-info/WHEEL
tts_webui_extension_megatts3-0.0.1.dist-info/top_level.txt
tts_webui_extension_megatts3-0.0.1.dist-info/RECORD
